odoo/addons/project_key/README.rst
odoo/addons/project_key/__init__.py
odoo/addons/project_key/__manifest__.py
odoo/addons/project_key/hooks.py
odoo/addons/project_key/controllers/__init__.py
odoo/addons/project_key/controllers/main.py
odoo/addons/project_key/i18n/de.po
odoo/addons/project_key/i18n/es_AR.po
odoo/addons/project_key/i18n/fr.po
odoo/addons/project_key/i18n/it.po
odoo/addons/project_key/i18n/project_key.pot
odoo/addons/project_key/models/__init__.py
odoo/addons/project_key/models/project_project.py
odoo/addons/project_key/models/project_task.py
odoo/addons/project_key/readme/CONTRIBUTORS.md
odoo/addons/project_key/readme/DESCRIPTION.md
odoo/addons/project_key/readme/USAGE.md
odoo/addons/project_key/static/description/icon.png
odoo/addons/project_key/static/description/index.html
odoo/addons/project_key/tests/__init__.py
odoo/addons/project_key/tests/test_common.py
odoo/addons/project_key/tests/test_controller.py
odoo/addons/project_key/tests/test_project.py
odoo/addons/project_key/tests/test_task.py
odoo/addons/project_key/views/project_key_views.xml
odoo_addon_project_key-18.0.1.0.0.5.dist-info/METADATA
odoo_addon_project_key-18.0.1.0.0.5.dist-info/WHEEL
odoo_addon_project_key-18.0.1.0.0.5.dist-info/top_level.txt
odoo_addon_project_key-18.0.1.0.0.5.dist-info/RECORD
