Metadata-Version: 2.1
Name: odoo-addon-project_key
Version: 18.0.1.0.0.5
Requires-Python: >=3.10
Requires-Dist: odoo==18.0.*
Summary: Module decorates projects and tasks with Project Key
Home-page: https://github.com/OCA/project
License: LGPL-3
Author: Modoolar, Odoo Community Association (OCA)
Author-email: support@odoo-community.org
Classifier: Programming Language :: Python
Classifier: Framework :: Odoo
Classifier: Framework :: Odoo :: 18.0
Classifier: License :: OSI Approved :: GNU Lesser General Public License v3 (LGPLv3)
